docugenr8/__init__.py
docugenr8/contents.py
docugenr8/document.py
docugenr8/settings.py
docugenr8-0.0.18.dist-info/LICENSE
docugenr8-0.0.18.dist-info/METADATA
docugenr8-0.0.18.dist-info/WHEEL
docugenr8-0.0.18.dist-info/top_level.txt
docugenr8-0.0.18.dist-info/RECORD
