Metadata-Version: 2.1
Name: docugenr8
Version: 0.0.18
Summary: Generates document with fonts, images, and elements using a coordinate system.
Author-email: Vladimir Jovanovic <vladimirjo@protonmail.com>
License: MIT
Keywords: document-generation,PDF,font-customization,image-integration,coordinate-system,text-formatting,python
Classifier: Programming Language :: Python :: 3
Requires-Python: >=3.10
License-File: LICENSE
Requires-Dist: docugenr8-core <1.0.0,>=0.0.0
Requires-Dist: docugenr8-pdf <1.0.0,>=0.0.0
Provides-Extra: build
Requires-Dist: build ; extra == 'build'
Requires-Dist: setuptools ; extra == 'build'
Requires-Dist: twine ; extra == 'build'
Provides-Extra: check
Requires-Dist: ruff ; extra == 'check'
Requires-Dist: mypy ; extra == 'check'
Provides-Extra: dev
Requires-Dist: docugenr8[build,check,test] ; extra == 'dev'
Provides-Extra: test
Requires-Dist: pytest ; extra == 'test'
Requires-Dist: pytest-cov ; extra == 'test'
